datacomp/__init__.py
datacomp/datacollection.py
datacomp/longitudinal.py
datacomp/prop_matching.py
datacomp/stats.py
datacomp/utils.py
datacomp/visualization.py
datacomp-0.0.6.dist-info/LICENSE
datacomp-0.0.6.dist-info/METADATA
datacomp-0.0.6.dist-info/WHEEL
datacomp-0.0.6.dist-info/top_level.txt
datacomp-0.0.6.dist-info/RECORD
