Metadata-Version: 2.1
Name: datacomp
Version: 0.0.6
Summary: Systematic comparisons of multiple datasets
Home-page: https://github.com/Cojabi/datacomp
Author: Colin Birkenbihl
Author-email: colin.birken@gmail.com
License: Apache 2.0 License
Platform: UNKNOWN
Classifier: Programming Language :: Python :: 3.6
Classifier: Programming Language :: Python :: 3.5
Classifier: Programming Language :: Python :: 3 :: Only
Classifier: Operating System :: OS Independent
Requires-Dist: pandas
Requires-Dist: xlrd
Requires-Dist: numpy
Requires-Dist: scipy
Requires-Dist: sklearn
Requires-Dist: matplotlib-venn
Requires-Dist: pymatch
Requires-Dist: matplotlib
Requires-Dist: statsmodels
Requires-Dist: seaborn
